<?xml version="1.0" encoding="UTF-8" standalone="yes"?>
<p:sld xmlns:a="http://schemas.openxmlformats.org/drawingml/2006/main" xmlns:r="http://schemas.openxmlformats.org/officeDocument/2006/relationships" xmlns:p="http://schemas.openxmlformats.org/presentationml/2006/main"><p:cSld><p:spTree><p:nvGrpSpPr><p:cNvPr id="1" name="Shape 158"/><p:cNvGrpSpPr/><p:nvPr/></p:nvGrpSpPr><p:grpSpPr><a:xfrm><a:off x="0" y="0"/><a:ext cx="0" cy="0"/><a:chOff x="0" y="0"/><a:chExt cx="0" cy="0"/></a:xfrm></p:grpSpPr><p:sp><p:nvSpPr><p:cNvPr id="159" name="Shape 159"/><p:cNvSpPr txBox="1"><a:spLocks noGrp="1"/></p:cNvSpPr><p:nvPr><p:ph type="title"/></p:nvPr></p:nvSpPr><p:spPr><a:xfrm><a:off x="457200" y="274637"/><a:ext cx="8229600" cy="1143000"/></a:xfrm><a:prstGeom prst="rect"><a:avLst/></a:prstGeom></p:spPr><p:txBody><a:bodyPr lIns="91425" tIns="91425" rIns="91425" bIns="91425" anchor="b" anchorCtr="0"><a:spAutoFit/></a:bodyPr><a:lstStyle/><a:p><a:pPr><a:buNone/></a:pPr><a:r><a:rPr lang="en"/><a:t>Effects on native fish species (NH</a:t></a:r><a:r><a:rPr lang="en" baseline="-25000"/><a:t>4</a:t></a:r><a:r><a:rPr lang="en"/><a:t>)</a:t></a:r></a:p></p:txBody></p:sp><p:sp><p:nvSpPr><p:cNvPr id="160" name="Shape 160"/><p:cNvSpPr txBox="1"><a:spLocks noGrp="1"/></p:cNvSpPr><p:nvPr><p:ph type="body" idx="1"/></p:nvPr></p:nvSpPr><p:spPr><a:xfrm><a:off x="457200" y="1396864"/><a:ext cx="8229600" cy="5171100"/></a:xfrm><a:prstGeom prst="rect"><a:avLst/></a:prstGeom></p:spPr><p:txBody><a:bodyPr lIns="91425" tIns="91425" rIns="91425" bIns="91425" anchor="t" anchorCtr="0"><a:spAutoFit/></a:bodyPr><a:lstStyle/><a:p><a:pPr marL="457200" lvl="0" indent="-381000" rtl="0"><a:buClr><a:srgbClr val="000000"/></a:buClr><a:buSzPct val="166666"/><a:buFont typeface="Arial"/><a:buChar char="•"/></a:pPr><a:r><a:rPr lang="en" sz="2400"/><a:t>Chronic exposure to ammonia in the water can cause the fish population to become stressed and cause damage to gills and other tissues. </a:t></a:r></a:p><a:p><a:pPr marL="457200" lvl="0" indent="-381000" rtl="0"><a:buClr><a:srgbClr val="000000"/></a:buClr><a:buSzPct val="166666"/><a:buFont typeface="Arial"/><a:buChar char="•"/></a:pPr><a:r><a:rPr lang="en" sz="2400"/><a:t>The damaged tissue caused by ammonia levels in the water leave the fish susceptible to bacterial infections and can stunt the growth of juvenile fish. (Floyd et al., 2005)</a:t></a:r></a:p><a:p><a:pPr marL="457200" lvl="0" indent="-381000" rtl="0"><a:buClr><a:srgbClr val="000000"/></a:buClr><a:buSzPct val="166666"/><a:buFont typeface="Arial"/><a:buChar char="•"/></a:pPr><a:r><a:rPr lang="en" sz="2400"/><a:t>High levels of ammonia are lethal to fish populations and will lead to large amounts of fish kill.   </a:t></a:r></a:p><a:p><a:endParaRPr lang="en" sz="2400"/></a:p></p:txBody></p:sp></p:spTree></p:cSld><p:clrMapOvr><a:masterClrMapping/></p:clrMapOvr><p:transition spd="slow"><p:cut/></p:transition></p:sld>